zookeeper_healthcheck/__init__.py
zookeeper_healthcheck/handler.py
zookeeper_healthcheck/health.py
zookeeper_healthcheck/main.py
zookeeper_healthcheck/parser.py
zookeeper_healthcheck/version.py
zookeeper_healthcheck-0.0.1.dist-info/LICENSE
zookeeper_healthcheck-0.0.1.dist-info/METADATA
zookeeper_healthcheck-0.0.1.dist-info/WHEEL
zookeeper_healthcheck-0.0.1.dist-info/entry_points.txt
zookeeper_healthcheck-0.0.1.dist-info/top_level.txt
zookeeper_healthcheck-0.0.1.dist-info/RECORD
