Metadata-Version: 2.1
Name: zookeeper-healthcheck
Version: 0.0.1
Summary: A simple healthcheck wrapper to monitor zookeeper.
Home-page: https://github.com/devshawn/zookeeper-healthcheck
Author: Shawn Seymour
Author-email: shawn@devshawn.com
License: Apache License 2.0
Keywords: zookeeper,health,healthcheck,wrapper,monitor
Platform: UNKNOWN
Classifier: Development Status :: 4 - Beta
Classifier: Intended Audience :: Developers
Classifier: Intended Audience :: System Administrators
Classifier: License :: OSI Approved :: Apache Software License
Classifier: Natural Language :: English
Classifier: Operating System :: MacOS
Classifier: Operating System :: Unix
Classifier: Programming Language :: Python :: 2
Classifier: Programming Language :: Python :: 2.7
Classifier: Programming Language :: Python :: 3
Classifier: Programming Language :: Python :: 3.5
Classifier: Programming Language :: Python :: 3.6
Classifier: Programming Language :: Python :: 3.7
Classifier: Topic :: Software Development
Classifier: Topic :: Software Development :: Libraries :: Python Modules
